{
    "$schema": "http://json-schema.org/draft-07/schema#",
    "properties": {
        "autoOpen": {
            "description": "should auto switch this workspace to encrypted workspace",
            "type": "boolean"
        },
        "exclude": {
            "default": "['.encrypt.json']",
            "items": {
                "type": "string"
            },
            "type": "array"
        },
        "extension": {
            "description": "This is auto-generated by extension, please do not edit this property directly.\nOther wise, it will cause the unknown problem.",
            "properties": {
                "exclude": {
                    "items": {
                        "type": "string"
                    },
                    "type": "array"
                },
                "include": {
                    "items": {
                        "type": "string"
                    },
                    "type": "array"
                }
            },
            "type": "object"
        },
        "include": {
            "default": [
                "**/*.md"
            ],
            "items": {
                "type": "string"
            },
            "type": "array"
        }
    },
    "type": "object"
}

